{"dependencies":[{"name":"C:/xampp/htdocs/portfolio/src/scss/base/_base.scss","includedInParent":true,"mtime":1517147810430},{"name":"C:/xampp/htdocs/portfolio/src/scss/base/_reset.scss","includedInParent":true,"mtime":1513778842381},{"name":"C:/xampp/htdocs/portfolio/src/scss/base/_utilities.scss","includedInParent":true,"mtime":1513779099947},{"name":"C:/xampp/htdocs/portfolio/src/scss/base/_variables.scss","includedInParent":true,"mtime":1513779279866},{"name":"C:/xampp/htdocs/portfolio/src/scss/layout/_layout.scss","includedInParent":true,"mtime":1513778621248},{"name":"C:/xampp/htdocs/portfolio/src/scss/modules/_modules.scss","includedInParent":true,"mtime":1513778621248},{"name":"C:/xampp/htdocs/portfolio/src/scss/states/_states.scss","includedInParent":true,"mtime":1513778621248},{"name":"C:\\xampp\\htdocs\\portfolio\\.postcssrc","includedInParent":true,"mtime":1517288511791},{"name":"_css_loader"}],"generated":{"css":"html, body, div, span, applet, object, iframe,\nh1, h2, h3, h4, h5, h6, p, blockquote, pre,\na, abbr, acronym, address, big, cite, code,\ndel, dfn, em, img, ins, kbd, q, s, samp,\nsmall, strike, strong, sub, sup, tt, var,\nb, u, i, center,\ndl, dt, dd, ol, ul, li,\nfieldset, form, label, legend,\ntable, caption, tbody, tfoot, thead, tr, th, td,\narticle, aside, canvas, details, embed,\nfigure, figcaption, footer, header, hgroup,\nmenu, nav, output, ruby, section, summary,\ntime, mark, audio, video {\n  margin: 0;\n  padding: 0;\n  border: 0;\n  font-size: 100%;\n  font: inherit;\n  vertical-align: baseline; }\n\n/* HTML5 display-role reset for older browsers */\narticle, aside, details, figcaption, figure,\nfooter, header, hgroup, menu, nav, section {\n  display: block; }\n\nbody {\n  line-height: 1; }\n\nol, ul {\n  list-style: none; }\n\nblockquote, q {\n  quotes: none; }\n\nblockquote:before, blockquote:after,\nq:before, q:after {\n  content: '';\n  content: none; }\n\ntable {\n  border-collapse: collapse;\n  border-spacing: 0; }\n","js":"\n        var reloadCSS = require('_css_loader');\n        module.hot.dispose(reloadCSS);\n        module.hot.accept(reloadCSS);\n      "},"hash":"e66e2ce8fb58311ffb6d33c2e8c162c6","cacheData":{}}